phylogenetic_tree_vis_comp/GridGeographicSvg.py
phylogenetic_tree_vis_comp/PhylogeneticTreeVisComp.py
phylogenetic_tree_vis_comp/TreeStructureSvg.py
phylogenetic_tree_vis_comp/__init__.py
phylogenetic_tree_vis_comp/_imports_.py
phylogenetic_tree_vis_comp/context.py
phylogenetic_tree_vis_comp/metadata.json
phylogenetic_tree_vis_comp/package-info.json
phylogenetic_tree_vis_comp/phylogenetic_tree_vis_comp.min.js
phylogenetic_tree_vis_comp/phylogenetic_tree_vis_comp.min.js.map
phylogenetic_tree_vis_comp-0.0.1.dist-info/LICENSE
phylogenetic_tree_vis_comp-0.0.1.dist-info/METADATA
phylogenetic_tree_vis_comp-0.0.1.dist-info/WHEEL
phylogenetic_tree_vis_comp-0.0.1.dist-info/top_level.txt
phylogenetic_tree_vis_comp-0.0.1.dist-info/RECORD
