Metadata-Version: 2.1
Name: phylogenetic_tree_vis_comp
Version: 0.0.1
Summary: Project Description
Author: Jiamei Lu <13609926401@163.com>
Classifier: Framework :: Dash
License-File: LICENSE
